fault/__init__.py
fault/action_generators.py
fault/actions.py
fault/array.py
fault/circuit_utils.py
fault/common.py
fault/cosa_target.py
fault/functional_tester.py
fault/logging.py
fault/magma_simulator_target.py
fault/random.py
fault/select_path.py
fault/symbolic_tester.py
fault/system_verilog_target.py
fault/target.py
fault/test_vector_generator.py
fault/test_vectors.py
fault/tester.py
fault/tuple.py
fault/util.py
fault/utils.py
fault/value.py
fault/value_utils.py
fault/vector_builder.py
fault/verilator_target.py
fault/verilator_utils.py
fault/verilog_target.py
fault/verilog_utils.py
fault/wrapper.py
fault-2.0.4.dist-info/LICENSE.txt
fault-2.0.4.dist-info/METADATA
fault-2.0.4.dist-info/PKG-INFO-e
fault-2.0.4.dist-info/PKG-INFO-e-e
fault-2.0.4.dist-info/SOURCES.txt-e
fault-2.0.4.dist-info/SOURCES.txt-e-e
fault-2.0.4.dist-info/WHEEL
fault-2.0.4.dist-info/dependency_links.txt-e
fault-2.0.4.dist-info/dependency_links.txt-e-e
fault-2.0.4.dist-info/requires.txt-e
fault-2.0.4.dist-info/requires.txt-e-e
fault-2.0.4.dist-info/top_level.txt
fault-2.0.4.dist-info/top_level.txt-e
fault-2.0.4.dist-info/top_level.txt-e-e
fault-2.0.4.dist-info/RECORD
