Metadata-Version: 2.1
Name: fault
Version: 2.0.4
Summary: A Python package for testing hardware (part of the magma ecosystem)
Home-page: https://github.com/leonardt/fault
Author: Leonard Truong
Author-email: lenny@cs.stanford.edu
License: BSD License
Platform: UNKNOWN
Requires-Python: >=3.6
Requires-Dist: astor
Requires-Dist: coreir (==2.0.*)
Requires-Dist: cosa
Requires-Dist: hwtypes (>=1.0.*)
